LICENSE
MANIFEST.in
README.md
setup.py
pyexamgen/ExamRenderer.py
pyexamgen/FriendlyArgumentParser.py
pyexamgen/PRNG.py
pyexamgen/RendererHelper.py
pyexamgen/WorkDir.py
pyexamgen/__init__.py
pyexamgen/__main__.py
pyexamgen.egg-info/PKG-INFO
pyexamgen.egg-info/SOURCES.txt
pyexamgen.egg-info/dependency_links.txt
pyexamgen.egg-info/entry_points.txt
pyexamgen.egg-info/requires.txt
pyexamgen.egg-info/top_level.txt
pyexamgen/templates/de-DE/base.tex
pyexamgen/templates/de-DE/common.tex